aioprometheus_thin/__init__.py
aioprometheus_thin/init_metrics.py
aioprometheus_thin/runner.py
aioprometheus_thin/configs/__init__.py
configs/__init__.py
tests/__init__.py
aioprometheus_thin-0.0.2.dist-info/METADATA
aioprometheus_thin-0.0.2.dist-info/WHEEL
aioprometheus_thin-0.0.2.dist-info/top_level.txt
aioprometheus_thin-0.0.2.dist-info/RECORD
