Metadata-Version: 2.1
Name: aioprometheus-thin
Version: 0.0.2
Summary: Python asyncIO Prometheus package - using aioprometheus, but simpler !
Home-page: https://github.com/RazcoDev/aioprometheus-thin
Author: Raz Co.
Author-email: razchn@gmail.com
License: UNKNOWN
Platform: UNKNOWN
Classifier: Programming Language :: Python :: 3
Classifier: License :: OSI Approved :: MIT License
Classifier: Operating System :: OS Independent
Requires-Python: >=3.6
Requires-Dist: aioprometheus
Requires-Dist: asyncio
